babeltalk/__init__.py
babeltalk/asr/__init__.py
babeltalk/asr/asr.py
babeltalk/nlp/__init__.py
babeltalk/tts/__init__.py
babeltalk/tts/tts.py
babeltalk/ui/__init__.py
babeltalk/ui/tts_demo.py
babeltalk-0.1.0.dist-info/LICENSE
babeltalk-0.1.0.dist-info/METADATA
babeltalk-0.1.0.dist-info/WHEEL
babeltalk-0.1.0.dist-info/top_level.txt
babeltalk-0.1.0.dist-info/RECORD
